kathra_core_model/__init__.py
kathra_core_model/model.py
kathra_core_model/utils.py
kathra_core_model-1.0.1.dist-info/LICENSE
kathra_core_model-1.0.1.dist-info/METADATA
kathra_core_model-1.0.1.dist-info/WHEEL
kathra_core_model-1.0.1.dist-info/top_level.txt
kathra_core_model-1.0.1.dist-info/RECORD
