Metadata-Version: 2.1
Name: kathra-core-model
Version: 1.0.1
Summary: Kathra Core Model
Home-page: https://gitlab.com/kathra/kathra-staging/kathra/kathra-core/kathra-core-python/kathra-core-model
Author: Julien Boubechtoula
Author-email: julien.boubechtoula@gmail.com
License: UNKNOWN
Keywords: Model,Core,Kathra
Platform: UNKNOWN
Classifier: Programming Language :: Python :: 3
Classifier: License :: OSI Approved :: Apache Software License
Classifier: Operating System :: OS Independent
Requires-Python: >=3.6
